eksiminer/__init__.py
eksiminer/core/__init__.py
eksiminer/core/base_driver.py
eksiminer/core/browser_factory.py
eksiminer/core/schemas.py
eksiminer/core/drivers/__init__.py
eksiminer/core/drivers/uc_driver.py
eksiminer/services/__init__.py
eksiminer/services/author_service.py
eksiminer/services/debe_service.py
eksiminer/services/entry_service.py
eksiminer/services/gundem_service.py
eksiminer/services/multiple_titles.py
eksiminer/services/selectors.py
eksiminer/services/topic_service.py
eksiminer/services/topic_url_service.py
eksiminer/services/util_service.py
eksiminer-0.0.2.dist-info/LICENCE.md
eksiminer-0.0.2.dist-info/METADATA
eksiminer-0.0.2.dist-info/WHEEL
eksiminer-0.0.2.dist-info/top_level.txt
eksiminer-0.0.2.dist-info/RECORD
