Metadata-Version: 2.1
Name: eksiminer
Version: 0.0.2
Summary: eksiminer is a Python package for scraping entries, topics, authors, and daily highlights from eksisozluk.com
Home-page: https://github.com/okanyenigun/eksi-scrap
Author: Okan Yenigün
Author-email: okanyenigun@gmail.com
License: MIT
Classifier: Development Status :: 3 - Alpha
Classifier: Intended Audience :: Developers
Classifier: Intended Audience :: Science/Research
Classifier: Topic :: Software Development :: Libraries :: Python Modules
Classifier: Topic :: Scientific/Engineering :: Mathematics
Classifier: License :: OSI Approved :: MIT License
Classifier: Programming Language :: Python :: 3
Classifier: Programming Language :: Python :: 3.7
Classifier: Programming Language :: Python :: 3.8
Classifier: Programming Language :: Python :: 3.9
Classifier: Programming Language :: Python :: 3.10
Classifier: Programming Language :: Python :: 3.11
Classifier: Operating System :: OS Independent
Requires-Python: >=3.7
License-File: LICENCE.md
Requires-Dist: selenium==4.28.1
Requires-Dist: beautifulsoup4==4.12.3
Requires-Dist: python-slugify==8.0.4
Requires-Dist: undetected-chromedriver==3.5.5
Requires-Dist: webdriver-manager==4.0.2
Requires-Dist: pydantic==2.11.7
